pytest_sort.py
pytest_python_test_engineer_sort-0.0.2.dist-info/entry_points.txt
pytest_python_test_engineer_sort-0.0.2.dist-info/LICENSE
pytest_python_test_engineer_sort-0.0.2.dist-info/WHEEL
pytest_python_test_engineer_sort-0.0.2.dist-info/METADATA
pytest_python_test_engineer_sort-0.0.2.dist-info/RECORD
