Metadata-Version: 2.1
Name: pytest-python-test-engineer-sort
Version: 0.0.2
Summary: Sort plugin for Pytest
Author-email: Craig West <craig@example.com>
Requires-Python: >=3.7
Classifier: License :: OSI Approved :: MIT License
Classifier: Framework :: Pytest
Requires-Dist: pytest>=6.2.0
Requires-Dist: tox ; extra == "test"
Project-URL: Home, https://github.com/python-test-engineer/Udemy-PyTest
Provides-Extra: test
